file_router/__init__.py
file_router/file_router_test.py
django_file_router-0.4.0.dist-info/LICENSE
django_file_router-0.4.0.dist-info/METADATA
django_file_router-0.4.0.dist-info/WHEEL
django_file_router-0.4.0.dist-info/top_level.txt
django_file_router-0.4.0.dist-info/RECORD
