Metadata-Version: 2.1
Name: django-file-router
Version: 0.4.0
Summary: File and folder-based routes for Django views
Home-page: https://github.com/jerivas/django-file-router
Author: Ed Rivas
Author-email: ed@jerivas.com
License: MIT
Project-URL: Documentation, https://github.com/jerivas/django-file-router#readme
Project-URL: Source, https://github.com/jerivas/django-file-router
Project-URL: Tracker, https://github.com/jerivas/django-file-router/issues
Project-URL: Changelog, https://github.com/jerivas/django-file-router/releases
Project-URL: Download, https://pypi.org/project/django-file-router/#files
Platform: UNKNOWN
Classifier: Development Status :: 4 - Beta
Classifier: Environment :: Web Environment
Classifier: Framework :: Django
Classifier: Intended Audience :: Developers
Classifier: Operating System :: OS Independent
Classifier: License :: OSI Approved :: MIT License
Classifier: Programming Language :: Python
Classifier: Programming Language :: Python :: 3
Classifier: Programming Language :: Python :: 3.7
Classifier: Programming Language :: Python :: 3.8
Classifier: Programming Language :: Python :: 3.9
Classifier: Programming Language :: Python :: 3.10
Classifier: Framework :: Django
Classifier: Framework :: Django :: 2.2
Classifier: Framework :: Django :: 3.0
Classifier: Framework :: Django :: 3.1
Classifier: Framework :: Django :: 3.2
Classifier: Framework :: Django :: 4.0
Requires-Python: >=3.7
License-File: LICENSE
Requires-Dist: django (>=2.2)
Provides-Extra: codestyle
Requires-Dist: flake8 (<4,>=3) ; extra == 'codestyle'
Requires-Dist: black (<23,>=22) ; extra == 'codestyle'
Requires-Dist: isort (<6,>=5) ; extra == 'codestyle'
Requires-Dist: pyupgrade (<3,>=2) ; extra == 'codestyle'
Provides-Extra: testing
Requires-Dist: pytest-django (<5,>=4) ; extra == 'testing'
Requires-Dist: pytest-cov (<3,>=2) ; extra == 'testing'
